MANIFEST.in
README.md
VERSION
setup.py
python/test/__init__.py
python/test/test_protos.py
python/voltha_protos/__init__.py
python/voltha_protos/adapter_pb2.py
python/voltha_protos/adapter_pb2_grpc.py
python/voltha_protos/adapter_service_pb2.py
python/voltha_protos/adapter_service_pb2_grpc.py
python/voltha_protos/common_pb2.py
python/voltha_protos/common_pb2_grpc.py
python/voltha_protos/core_adapter_pb2.py
python/voltha_protos/core_adapter_pb2_grpc.py
python/voltha_protos/core_pb2.py
python/voltha_protos/core_pb2_grpc.py
python/voltha_protos/core_services_pb2.py
python/voltha_protos/core_services_pb2_grpc.py
python/voltha_protos/device_pb2.py
python/voltha_protos/device_pb2_grpc.py
python/voltha_protos/events_pb2.py
python/voltha_protos/events_pb2_grpc.py
python/voltha_protos/ext_config_pb2.py
python/voltha_protos/ext_config_pb2_grpc.py
python/voltha_protos/extensions_pb2.py
python/voltha_protos/extensions_pb2_grpc.py
python/voltha_protos/health_pb2.py
python/voltha_protos/health_pb2_grpc.py
python/voltha_protos/ietf_interfaces_pb2.py
python/voltha_protos/ietf_interfaces_pb2_grpc.py
python/voltha_protos/inter_adapter_pb2.py
python/voltha_protos/inter_adapter_pb2_grpc.py
python/voltha_protos/logical_device_pb2.py
python/voltha_protos/logical_device_pb2_grpc.py
python/voltha_protos/olt_inter_adapter_service_pb2.py
python/voltha_protos/olt_inter_adapter_service_pb2_grpc.py
python/voltha_protos/omci_alarm_db_pb2.py
python/voltha_protos/omci_alarm_db_pb2_grpc.py
python/voltha_protos/omci_mib_db_pb2.py
python/voltha_protos/omci_mib_db_pb2_grpc.py
python/voltha_protos/omci_test_pb2.py
python/voltha_protos/omci_test_pb2_grpc.py
python/voltha_protos/onu_inter_adapter_service_pb2.py
python/voltha_protos/onu_inter_adapter_service_pb2_grpc.py
python/voltha_protos/openflow_13_pb2.py
python/voltha_protos/openflow_13_pb2_grpc.py
python/voltha_protos/openolt_pb2.py
python/voltha_protos/openolt_pb2_grpc.py
python/voltha_protos/tech_profile_pb2.py
python/voltha_protos.egg-info/PKG-INFO
python/voltha_protos.egg-info/SOURCES.txt
python/voltha_protos.egg-info/dependency_links.txt
python/voltha_protos.egg-info/requires.txt
python/voltha_protos.egg-info/top_level.txt