Metadata-Version: 1.1
Name: voltha-protos
Version: 5.6.3
Summary: Protobuf interface definitions
Home-page: https://gerrit.opencord.org/gitweb?p=voltha-protos.git
Author: VOLTHA project
Author-email: voltha-dev@opencord.org
License: Apache Software License
Keywords: protobuf voltha
Platform: UNKNOWN
Classifier: Development Status :: 5 - Production/Stable
Classifier: Intended Audience :: Developers
Classifier: License :: OSI Approved :: Apache Software License
Classifier: Programming Language :: Python :: 3.5
Classifier: Programming Language :: Python :: 3.6
Classifier: Programming Language :: Python :: 3.7
